mlrl/__init__.py
mlrl/seco/__init__.py
mlrl/seco/learners.py
mlrl/seco/package_info.py
mlrl/seco/config/__init__.py
mlrl/seco/config/parameters.py
mlrl/seco/cython/__init__.py
mlrl/seco/cython/heuristic.cp312-win_arm64.lib
mlrl/seco/cython/heuristic.cp312-win_arm64.pyd
mlrl/seco/cython/learner.cp312-win_arm64.lib
mlrl/seco/cython/learner.cp312-win_arm64.pyd
mlrl/seco/cython/learner_seco.cp312-win_arm64.lib
mlrl/seco/cython/learner_seco.cp312-win_arm64.pyd
mlrl/seco/cython/lift_function.cp312-win_arm64.lib
mlrl/seco/cython/lift_function.cp312-win_arm64.pyd
mlrl/seco/cython/mlrlseco-0.dll
mlrl/seco/cython/mlrlseco.lib
mlrl/seco/cython/package_info.cp312-win_arm64.lib
mlrl/seco/cython/package_info.cp312-win_arm64.pyd
mlrl/seco/cython/stopping_criterion.cp312-win_arm64.lib
mlrl/seco/cython/stopping_criterion.cp312-win_arm64.pyd
mlrl/seco/testbed/__init__.py
mlrl/seco/testbed/runnables.py
mlrl_seco-0.15.1.dist-info/METADATA
mlrl_seco-0.15.1.dist-info/WHEEL
mlrl_seco-0.15.1.dist-info/top_level.txt
mlrl_seco-0.15.1.dist-info/RECORD
