Metadata-Version: 2.4
Name: mlrl-seco
Version: 0.15.1
Summary: A scikit-learn implementation of a Separate-and-Conquer (SeCo) multi-label rule learning algorithm
Author-email: Michael Rapp <michael.rapp.ml@gmail.com>
License-Expression: MIT
Project-URL: homepage, https://github.com/mrapp-ke/MLRL-Boomer
Project-URL: source, https://github.com/mrapp-ke/MLRL-Boomer.git
Project-URL: download, https://github.com/mrapp-ke/MLRL-Boomer/releases
Project-URL: changelog, https://raw.githubusercontent.com/mrapp-ke/MLRL-Boomer/refs/heads/main/CHANGELOG.md
Project-URL: documentation, https://mlrl-boomer.readthedocs.io/en/latest
Project-URL: issues, https://github.com/mrapp-ke/MLRL-Boomer/issues
Keywords: machine learning,multi-label classification,rule learning,scikit-learn,separate-and-conquer
Classifier: Development Status :: 5 - Production/Stable
Classifier: Intended Audience :: Science/Research
Classifier: Operating System :: MacOS
Classifier: Operating System :: Microsoft :: Windows
Classifier: Operating System :: POSIX :: Linux
Classifier: Programming Language :: C++
Classifier: Programming Language :: Cython
Classifier: Programming Language :: Python :: 3
Classifier: Topic :: Scientific/Engineering :: Artificial Intelligence
Classifier: Topic :: Software Development :: Libraries :: Python Modules
Requires-Python: >=3.12
Requires-Dist: mlrl-common==0.15.1
